tamplar/__init__.py
tamplar/__cmd/main.py
tamplar/__internal/init.py
tamplar/__internal/utils.py
tamplar/api/__init__.py
tamplar/api/methods.py
tamplar/tests/__init__.py
tamplar/tests/test_clean.py
tamplar/tests/test_run.py
tamplar/tests/utils.py
tamplar/tests/run/__init__.py
tamplar/tests/run/test_env.py
tamplar/tests/run/test_full_build.py
tamplar/tests/run/test_full_cached.py
tamplar/tests/test_init/__init__.py
tamplar/tests/test_init/test_empty.py
tamplar/tests/test_init/test_not_empty.py
tamplar-0.5.1.dist-info/METADATA
tamplar-0.5.1.dist-info/WHEEL
tamplar-0.5.1.dist-info/entry_points.txt
tamplar-0.5.1.dist-info/top_level.txt
tamplar-0.5.1.dist-info/RECORD
