Metadata-Version: 2.1
Name: tamplar
Version: 0.5.1
Summary: This util creates new service of python. This one has some additional command cli for control of development
Home-page: https://github.com/Hedgehogues/tamplar
Author: Urvanov Egor
Author-email: hedgehogues@bk.ru
License: UNKNOWN
Platform: UNKNOWN
Classifier: Programming Language :: Python :: 3.7
Classifier: Operating System :: OS Independent
Requires-Dist: GitPython (==3.1.2)
Requires-Dist: docker-compose (==1.25.5)
Requires-Dist: fire (==0.3.1)
Requires-Dist: pytest (==5.4.2)
Requires-Dist: Jinja2 (==2.11.2)
